ChangeLog
INSTALL
LICENSE
MANIFEST.in
README.rst
TODO
demo.py
poppler-annotation.sip
poppler-convert.sip
poppler-document.sip
poppler-embedded-file.sip
poppler-font-info.sip
poppler-font-iterator.sip
poppler-form.sip
poppler-link-destination.sip
poppler-link.sip
poppler-movie-object.sip
poppler-opt-content-model.sip
poppler-page-transition.sip
poppler-page.sip
poppler-qt4.sip
poppler-sound-object.sip
poppler-text-box.sip
setup.cfg
setup.py
types.sip
python_poppler_qt4.egg-info/PKG-INFO
python_poppler_qt4.egg-info/SOURCES.txt
python_poppler_qt4.egg-info/dependency_links.txt
python_poppler_qt4.egg-info/top_level.txt