Metadata-Version: 1.1
Name: python-poppler-qt4
Version: 0.24.0
Summary: A Python binding to Poppler-Qt4
Home-page: https://github.com/wbsoft/python-poppler-qt4
Author: Wilbert Berendsen
Author-email: wbsoft@xs4all.nl
License: LGPL
Platform: UNKNOWN
Classifier: Development Status :: 5 - Production/Stable
Classifier: Intended Audience :: Developers
Classifier: License :: OSI Approved :: GNU Library or Lesser General Public License (LGPL)
Classifier: Operating System :: MacOS :: MacOS X
Classifier: Operating System :: Microsoft :: Windows
Classifier: Operating System :: POSIX
Classifier: Programming Language :: Python
Classifier: Programming Language :: Python :: 2.6
Classifier: Programming Language :: Python :: 2.7
Classifier: Programming Language :: Python :: 3
Classifier: Topic :: Multimedia :: Graphics :: Viewers
